blurhash_rs/__init__.py
blurhash_rs/_lib.cpython-312-x86_64-linux-musl.so
blurhash_rs/py.typed
blurhash_rs.libs/libgcc_s-0cd532bd.so.1
blurhash_rs-1.0.0.dist-info/METADATA
blurhash_rs-1.0.0.dist-info/WHEEL
blurhash_rs-1.0.0.dist-info/RECORD
blurhash_rs-1.0.0.dist-info/sboms/auditwheel.cdx.json
