Metadata-Version: 2.4
Name: blurhash-rs
Version: 1.0.0
Classifier: Development Status :: 5 - Production/Stable
Classifier: Intended Audience :: Developers
Classifier: License :: OSI Approved :: MIT License
Classifier: Operating System :: OS Independent
Classifier: Programming Language :: Python :: 3.9
Classifier: Programming Language :: Python :: 3.10
Classifier: Programming Language :: Python :: 3.11
Classifier: Programming Language :: Python :: 3.12
Classifier: Programming Language :: Python :: 3.13
Classifier: Programming Language :: Python :: 3.14
Classifier: Programming Language :: Python :: Implementation :: CPython
Classifier: Programming Language :: Python :: Implementation :: PyPy
Classifier: Programming Language :: Rust
Classifier: Topic :: Multimedia :: Graphics
Classifier: Topic :: Software Development :: Libraries :: Python Modules
Classifier: Typing :: Typed
Requires-Dist: pillow>=9.0.0
Summary: High-performance BlurHash encoder/decoder
Keywords: blurhash,decoder,encoder,image,loading,placeholder,preview,progressive
Author-email: Kamil Monicz <kamil@monicz.dev>
License-Expression: MIT
Requires-Python: >=3.9
Project-URL: Issues, https://github.com/Zaczero/pkgs/issues
Project-URL: Repository, https://github.com/Zaczero/pkgs/tree/main/blurhash-rs
